{
    "Racer": {
        "checkpoints": [
            {
                "steps": 6016,
                "file_path": "results\\Racer\\Racer\\Racer-6016.onnx",
                "reward": null,
                "creation_time": 1717494673.3914914,
                "auxillary_file_paths": [
                    "results\\Racer\\Racer\\Racer-6016.pt"
                ]
            }
        ],
        "final_checkpoint": {
            "steps": 6016,
            "file_path": "results\\Racer\\Racer.onnx",
            "reward": null,
            "creation_time": 1717494673.3914914,
            "auxillary_file_paths": [
                "results\\Racer\\Racer\\Racer-6016.pt"
            ]
        }
    },
    "metadata": {
        "stats_format_version": "0.3.0",
        "mlagents_version": "0.30.0",
        "torch_version": "1.7.1+cu110"
    }
}